micrompn/__init__.py
micrompn/_version.py
micrompn/main.py
micrompn/mpn.py
micrompn/data/example1-output.csv
micrompn/data/example1_mapfile.toml
micrompn/data/example1_plate_data.csv
micrompn/data/additional_plate_layout_examples/micrompn_384_mock/384_4_samples/384_4_samples_horizontal_dilutions.csv
micrompn/data/additional_plate_layout_examples/micrompn_384_mock/384_4_samples/OUTFILE_384_4_samples_horizontal_dilutions.csv
micrompn/data/additional_plate_layout_examples/micrompn_384_mock/384_4_samples/microplate_384_4_samples_horizontal_dilutions.txt
micrompn/data/additional_plate_layout_examples/micrompn_384_mock/384_6_samples/384_6_samples_vertical_dilutions.csv
micrompn/data/additional_plate_layout_examples/micrompn_384_mock/384_6_samples/OUTFILE_384_6_samples_vertical_dilutions.csv
micrompn/data/additional_plate_layout_examples/micrompn_384_mock/384_6_samples/microplate_384_6_samples_vertical_dilutions.txt
micrompn/data/additional_plate_layout_examples/micrompn_96_mock/96_2_samples_horizontal_dilutions/96_2_samples_horizontal_dilutions.csv
micrompn/data/additional_plate_layout_examples/micrompn_96_mock/96_2_samples_horizontal_dilutions/OUTFILE_96_2_samples_horizontal_dilutions.csv
micrompn/data/additional_plate_layout_examples/micrompn_96_mock/96_2_samples_horizontal_dilutions/microplate_96_2_samples_horizontal_dilutions.txt
micrompn/data/additional_plate_layout_examples/micrompn_96_mock/96_2_samples_vertical_dilutions/96_2_samples_vertical_dilutions.csv
micrompn/data/additional_plate_layout_examples/micrompn_96_mock/96_3_samples_vertical_dilutions/96_3_samples_vertical_dilutions.csv
micrompn/data/additional_plate_layout_examples/micrompn_96_mock/96_3_samples_vertical_dilutions/OUTFILE_96_2_samples_vertical_dilutions.csv
micrompn/data/additional_plate_layout_examples/micrompn_96_mock/96_3_samples_vertical_dilutions/OUTFILE_96_3_samples_vertical_dilutions.csv
micrompn-1.0.1.dist-info/METADATA
micrompn-1.0.1.dist-info/WHEEL
micrompn-1.0.1.dist-info/entry_points.txt
micrompn-1.0.1.dist-info/top_level.txt
micrompn-1.0.1.dist-info/RECORD
