Metadata-Version: 2.1
Name: micrompn
Version: 1.0.1
Summary: MicroMPN: Software to estimate Most Probable Number (MPN) bacterial abundance from microplates. 
Author-email: "Adam R. Rivers" <adam.rivers@usda.gov>
License: CC0
Keywords: microbiology,mpn
Classifier: License :: CC0 1.0 Universal (CC0 1.0) Public Domain Dedication
Classifier: Topic :: Scientific/Engineering :: Bio-Informatics
Classifier: Programming Language :: Python :: 3.11
Classifier: Programming Language :: Python :: 3.10
Classifier: Programming Language :: Python :: 3.9
Classifier: Programming Language :: Python :: 3.8
Requires-Python: >=3.8
Requires-Dist: pandas
Requires-Dist: numpy
Requires-Dist: scipy
Requires-Dist: wellmap
Requires-Dist: matplotlib
